segmentools/__init__.py
segmentools/augmentation.py
segmentools/dataset.py
segmentools/evaluation.py
segmentools/inference.py
segmentools/metrics.py
segmentools/prepare_data.py
segmentools/trainer.py
segmentools/version.py
segmentools/utils/__init__.py
segmentools/utils/evaluation.py
segmentools/utils/inference.py
segmentools/utils/metrics.py
segmentools/utils/trainning.py
segmentools/utils/visualisation.py
segmentools-0.1.0.dist-info/LICENSE.txt
segmentools-0.1.0.dist-info/METADATA
segmentools-0.1.0.dist-info/WHEEL
segmentools-0.1.0.dist-info/top_level.txt
segmentools-0.1.0.dist-info/RECORD
