Metadata-Version: 2.1
Name: segmentools
Version: 0.1.0
Summary: Segmentools provide low and high levels utilities to train, evaluate and deploy models. Low levels classes and functions are usefull develop new method while keeping data formats uniforms and high level classes allow to write scripts in a very concise and understable way.
Author-email: Lucas Bernigaud Samatan <lucas.bernigaud-samatan@inrae.fr>, Jordan Bernigaud Samatan <jordan.bernigaud-samatan@inrae.fr>
Maintainer-email: Jordan Bernigaud Samatan <jordan.bernigaud-samatan@inrae.fr>
License: The MIT License (MIT)
Project-URL: Homepage, https://forgemia.inra.fr/ue-apc/librairies/python/segmentools
Project-URL: Issues, https://forgemia.inra.fr/ue-apc/librairies/python/segmentools/-/issues
Classifier: Development Status :: 3 - Alpha
Classifier: Programming Language :: Python :: 3
Classifier: Programming Language :: Python :: 3.10
Classifier: Programming Language :: Python :: 3.11
Requires-Python: >=3.10.12
License-File: LICENSE.txt
Requires-Dist: computervisiontools
Requires-Dist: matplotlib ==3.8.2
Requires-Dist: torch ==2.1.0
Requires-Dist: torchvision ==0.16.0
Requires-Dist: pandas ==2.1.4
Requires-Dist: tensorboard ==2.15.1
Requires-Dist: XlsxWriter ==3.1.9
Requires-Dist: openpyxl ==3.1.2
Requires-Dist: seaborn ==0.13.0
Requires-Dist: torchgeometry ==0.1.2
Requires-Dist: torchmetrics ==1.3.0
